shofash/__init__.py
shofash/compile.py
shofash/sayError.py
shofash/shofash_default_menu.py
shofash/shofash_expandMacros.py
shofash/shofash_functions.py
shofash/shofash_getCommand.py
shofash/shofash_html.py
shofash/shofash_index.py
shofash/shofash_write_html.py
shofash/tardir.py
shofash/tarfile.py
shofash/validate.py
shofash-2.dist-info/LICENSE
shofash-2.dist-info/METADATA
shofash-2.dist-info/WHEEL
shofash-2.dist-info/top_level.txt
shofash-2.dist-info/RECORD
