Metadata-Version: 2.1
Name: shofash
Version: 2
Summary: A simple HTML compiler
Home-page: https://www.intershed.co.uk/Free_software/shofash/Version_2/index.html
Author: Frazer Melton
Author-email: fmm@intershed.co.uk
License: UNKNOWN
Project-URL: Manual, https://www.intershed.co.uk/Free_software/shofash/Version_2/Manual/index.html
Platform: UNKNOWN
Classifier: Programming Language :: Python :: 3
Classifier: License :: OSI Approved :: GNU General Public License v3 or later (GPLv3+)
Classifier: Operating System :: OS Independent
Requires-Python: >=3.6
License-File: LICENSE
